a_selenium_get_with_timeout/LICENSE
a_selenium_get_with_timeout/README.MD
a_selenium_get_with_timeout/__init__.py
a_selenium_get_with_timeout/requirements.txt
a_selenium_get_with_timeout/thirdparty.json
a_selenium_get_with_timeout-0.11.dist-info/LICENSE.rst
a_selenium_get_with_timeout-0.11.dist-info/METADATA
a_selenium_get_with_timeout-0.11.dist-info/WHEEL
a_selenium_get_with_timeout-0.11.dist-info/top_level.txt
a_selenium_get_with_timeout-0.11.dist-info/RECORD
